eventisc/__init__.py
eventisc/celery_listener.py
eventisc/http_listener.py
eventisc/rabbit_listener.py
event_isc-0.1.0.dist-info/LICENSE.txt
event_isc-0.1.0.dist-info/METADATA
event_isc-0.1.0.dist-info/WHEEL
event_isc-0.1.0.dist-info/top_level.txt
event_isc-0.1.0.dist-info/RECORD
