Metadata-Version: 2.1
Name: event-isc
Version: 0.1.0
Summary: Library for inter-service event-based communication
Home-page: https://github.com/radiocut/event-isc/
Author: Guillermo Narvaja
Author-email: guillermo.narvaja@radiocut.fm
License: UNKNOWN
Project-URL: Bug Reports, https://github.com/radiocutfm/event-isc/issues
Project-URL: Funding, https://donate.pypi.org
Project-URL: Say Thanks!, https://saythanks.io/to/guillermo.narvaja%40radiocut.fm
Project-URL: Source, https://github.com/radiocutfm/event-isc/
Keywords: event inter-service-communication celery microservices
Platform: UNKNOWN
Classifier: Development Status :: 3 - Alpha
Classifier: Intended Audience :: Developers
Classifier: License :: OSI Approved :: MIT License
Classifier: Programming Language :: Python :: 3
Classifier: Programming Language :: Python :: 3.6
Classifier: Programming Language :: Python :: 3.7
Classifier: Programming Language :: Python :: 3.8
Requires-Python: >=3.6, !=3.0.*, !=3.1.*, !=3.2.*, !=3.3.*, !=3.4.*, <4
License-File: LICENSE.txt
Requires-Dist: environs
Requires-Dist: pyyaml
Provides-Extra: celery
Requires-Dist: celery ; extra == 'celery'
Provides-Extra: dev
Requires-Dist: check-manifest ; extra == 'dev'
Requires-Dist: responses ; extra == 'dev'
Requires-Dist: celery ; extra == 'dev'
Requires-Dist: requests ; extra == 'dev'
Requires-Dist: pika ; extra == 'dev'
Provides-Extra: pika
Requires-Dist: pika ; extra == 'pika'
Provides-Extra: requests
Requires-Dist: requests ; extra == 'requests'
Provides-Extra: test
Requires-Dist: coverage ; extra == 'test'
Requires-Dist: responses ; extra == 'test'
Requires-Dist: celery ; extra == 'test'
Requires-Dist: requests ; extra == 'test'
Requires-Dist: pika ; extra == 'test'
